MOVE = "MOVE"
LOADK = "LOADK"
LOADKX = "LOADKX"
LOADBOOL = "LOADBOOL"
LOADNIL = "LOADNIL"
GETUPVAL = "GETUPVAL"
GETTABUP = "GETTABUP"

GETTABLE = "GETTABLE"
SETTABUP = "SETTABUP"
SETUPVAL = "SETUPVAL"
SETTABLE = "SETTABLE"
NEWTABLE = "NEWTABLE"

SELF = "SELF"
ADD = "ADD"
SUB = "SUB"
MUL = "MUL"
MOD = "MOD"
POW = "POW"
DIV = "DIV"

IDIV = "IDIV"
BAND = "BAND"
BOR = "BOR"
BXOR = "BXOR"
SHL = "SHL"
SHR = "SHR"
UNM = "UNM"
BNOT = "BNOT"

NOT = "NOT"
LEN = "LEN"
CONCAT = "CONCAT"
JMP = "JMP"
EQ = "EQ"
LT = "LT"
LE = "LE"
TEST = "TEST"

TESTSET = "TESTSET"
CALL = "CALL"
TAILCALL = "TAILCALL"
RETURN = "RETURN"
FORLOOP = "FORLOOP"
FORPREP = "FORPREP"

TFORCALL = "TFORCALL"
TFORLOOP = "TFORLOOP"
SETLIST = "SETLIST"
CLOSURE = "CLOSURE"
VARARG = "VARARG"
EXTRAARG = "EXTRAARG"
